wagtail_user_workspace/__init__.py
wagtail_user_workspace/apps.py
wagtail_user_workspace/checks.py
wagtail_user_workspace/handlers.py
wagtail_user_workspace/models.py
wagtail_user_workspace/settings.py
wagtail_user_workspace/utils.py
wagtail_user_workspace/management/commands/createuserworkspaces.py
wagtail_user_workspace/migrations/__init__.py
wagtail_user_workspace-0.1.0.dev0.dist-info/LICENSE
wagtail_user_workspace-0.1.0.dev0.dist-info/METADATA
wagtail_user_workspace-0.1.0.dev0.dist-info/WHEEL
wagtail_user_workspace-0.1.0.dev0.dist-info/top_level.txt
wagtail_user_workspace-0.1.0.dev0.dist-info/RECORD
