Metadata-Version: 2.1
Name: wagtail-user-workspace
Version: 0.1.0.dev0
Summary: Wagtail workspace page for every registred user.
Author-email: "LESPROJEKT-SLUŽBY s.r.o." <support@hub4everybody.com>
Project-URL: Homepage, https://github.com/LESPROJEKT/wagtail-user-workspace
Project-URL: Bug Tracker, https://github.com/LESPROJEKT/wagtail-user-workspace/issues
Classifier: Programming Language :: Python :: 3
Classifier: Intended Audience :: Developers
Classifier: Operating System :: OS Independent
Requires-Python: >=3.7
License-File: LICENSE
Requires-Dist: wagtail ==4.*
Requires-Dist: django-solo
Requires-Dist: django-allauth
